just4fun/__init__.py
just4fun/__main__.py
just4fun/fun.py
just4fun-0.1.1.dist-info/LICENSE
just4fun-0.1.1.dist-info/METADATA
just4fun-0.1.1.dist-info/WHEEL
just4fun-0.1.1.dist-info/entry_points.txt
just4fun-0.1.1.dist-info/top_level.txt
just4fun-0.1.1.dist-info/RECORD
