Metadata-Version: 2.1
Name: just4fun
Version: 0.1.1
Summary: A fun package with 4 interactive functions for your entertainment.
Author-email: Edison Chen <edison.chen@stern.nyu.edu>, Natalie Wu <nw2132@nyu.edu>, Jacklyn Hu <jh7535@nyu.edu>, Chelsea Li <cl5251@nyu.edu>
License: GNU GENERAL PUBLIC LICENSE
Project-URL: Homepage, https://github.com/software-students-spring2024/3-python-package-exercise-bestswe/tree/main
Keywords: python,package,build,tutorial
Classifier: Programming Language :: Python :: 3
Classifier: Intended Audience :: Education
Classifier: License :: OSI Approved :: GNU General Public License v3 (GPLv3)
Classifier: Operating System :: OS Independent
Requires-Python: >=3.7
License-File: LICENSE
Provides-Extra: dev
Requires-Dist: pytest ; extra == 'dev'
